README.rst
setup.py
quantulum/__init__.py
quantulum/classes.py
quantulum/classifier.py
quantulum/clf.pickle
quantulum/entities.json
quantulum/load.py
quantulum/parser.py
quantulum/regex.py
quantulum/tests.json
quantulum/tests.py
quantulum/train.json
quantulum/units.json
quantulum/wiki.json
quantulum.egg-info/PKG-INFO
quantulum.egg-info/SOURCES.txt
quantulum.egg-info/dependency_links.txt
quantulum.egg-info/requires.txt
quantulum.egg-info/top_level.txt