Metadata-Version: 1.1
Name: quantulum
Version: 0.1.11
Summary: Extract quantities from unstructured text.
Home-page: https://github.com/marcolagi/quantulum
Author: Marco Lagi
Author-email: marco dot neri dot lagi at gmail dot com
License: MIT
Download-URL: https://github.com/marcolagi/quantulum/tarball/0.1
Keywords: information extraction,quantities,units,measurements,nlp,natural language processing,text mining,text processing
Platform: UNKNOWN
Classifier: Intended Audience :: Developers
Classifier: Intended Audience :: Science/Research
Classifier: Operating System :: MacOS :: MacOS X
Classifier: Operating System :: Microsoft :: Windows
Classifier: Operating System :: POSIX
Classifier: License :: OSI Approved :: MIT License
Classifier: Programming Language :: Python
Classifier: Programming Language :: Python :: 2.7
Classifier: Development Status :: 3 - Alpha
Classifier: Natural Language :: English
Classifier: Topic :: Software Development :: Libraries :: Python Modules
Classifier: Topic :: Text Processing :: Linguistic
Classifier: Topic :: Scientific/Engineering
